signature/__init__.py
signature/config.py
signature/data.py
signature/example.py
signature/inference.py
signature/models.py
signature/training.py
signature/utils.py
signature/models/__init__.py
signature/models/factory.py
signature/models/losses/__init__.py
signature/models/losses/arcface.py
signature/models/losses/contrastive.py
signature/models/resnet_siamese/__init__.py
signature/models/resnet_siamese/model.py
signature/models/vit/__init__.py
signature/models/vit/model.py
litewave_ml_models_signature-0.0.12.dist-info/METADATA
litewave_ml_models_signature-0.0.12.dist-info/WHEEL
litewave_ml_models_signature-0.0.12.dist-info/top_level.txt
litewave_ml_models_signature-0.0.12.dist-info/RECORD
