Metadata-Version: 2.4
Name: litewave-ml-models-signature
Version: 0.0.12
Summary: A package for signature verification and classification.
Home-page: https://github.com/aiorch/litewave-ml-models/tree/main/signature
Author: LitewaveAI
Author-email: LitewaveAI <yash@litewave.ai>
Maintainer-email: LitewaveAI <yash@litewave.ai>
License: MIT
Project-URL: Homepage, https://github.com/aiorch/litewave-ml-models/tree/main/signature
Project-URL: Documentation, https://github.com/aiorch/litewave-ml-models/blob/main/signature/README.md
Project-URL: Repository, https://github.com/aiorch/litewave-ml-models/tree/main/signature
Project-URL: Bug Tracker, https://github.com/aiorch/litewave-ml-models/tree/main/signatureissues
Keywords: signature,verification,classification,machine-learning,computer-vision,pytorch
Classifier: Development Status :: 4 - Beta
Classifier: Intended Audience :: Science/Research
Classifier: Intended Audience :: Manufacturing
Classifier: Topic :: Scientific/Engineering :: Artificial Intelligence
Classifier: Topic :: Scientific/Engineering :: Image Processing
Classifier: License :: OSI Approved :: MIT License
Classifier: Programming Language :: Python :: 3
Classifier: Programming Language :: Python :: 3.8
Classifier: Programming Language :: Python :: 3.9
Classifier: Programming Language :: Python :: 3.10
Classifier: Programming Language :: Python :: 3.11
Classifier: Programming Language :: Python :: 3.12
Requires-Python: >=3.8
Requires-Dist: torch>=1.9.0
Requires-Dist: torchvision>=0.10.0
Requires-Dist: timm>=0.9.0
Requires-Dist: scikit-image>=0.19.0
Requires-Dist: pillow>=8.0.0
Requires-Dist: opencv-python>=4.5.0
Requires-Dist: numpy>=1.21.0
Requires-Dist: scipy>=1.7.0
Requires-Dist: scikit-learn>=1.0.0
Requires-Dist: pandas>=1.3.0
Requires-Dist: pydantic>=1.8.0
Requires-Dist: pydantic-settings>=2.0.0
Requires-Dist: boto3>=1.20.0
Requires-Dist: tqdm>=4.60.0
Requires-Dist: matplotlib>=3.5.0
Requires-Dist: typing-extensions>=4.0.0
Provides-Extra: dev
Requires-Dist: pytest>=6.0; extra == "dev"
Requires-Dist: pytest-cov; extra == "dev"
Requires-Dist: black; extra == "dev"
Requires-Dist: flake8; extra == "dev"
Requires-Dist: mypy; extra == "dev"
Requires-Dist: isort; extra == "dev"
Provides-Extra: docs
Requires-Dist: sphinx; extra == "docs"
Requires-Dist: sphinx-rtd-theme; extra == "docs"
Dynamic: author
Dynamic: home-page
Dynamic: requires-python
